tests/__init__.py
tests/test_engine.py
tests/test_room.py
text_adventure/__init__.py
text_adventure/engine.py
text_adventure/room.py
text_adventure_framework-0.1.2.dist-info/METADATA
text_adventure_framework-0.1.2.dist-info/WHEEL
text_adventure_framework-0.1.2.dist-info/top_level.txt
text_adventure_framework-0.1.2.dist-info/RECORD
