Metadata-Version: 2.1
Name: text-adventure-framework
Version: 0.1.2
Summary: A simple text adventure building framework
Home-page: https://github.com/caesurus/text_adventure
Author: Caesurus
Author-email: caesurus+textadventure@gmail.com
License: UNKNOWN
Project-URL: Bug Tracker, https://github.com/caesurus/text_adventure/issues
Platform: UNKNOWN
Classifier: Programming Language :: Python :: 3
Classifier: License :: OSI Approved :: MIT License
Classifier: Operating System :: OS Independent
Requires-Python: >=3.6
